substack/__init__.py
substack/api.py
substack/exceptions.py
substack/post.py
python_substack-0.1.17.dist-info/METADATA
python_substack-0.1.17.dist-info/WHEEL
python_substack-0.1.17.dist-info/licenses/LICENSE
python_substack-0.1.17.dist-info/RECORD
