Metadata-Version: 2.4
Name: python-substack
Version: 0.1.17
Summary: A Python wrapper around the Substack API.
License: MIT
License-File: LICENSE
Keywords: substack
Author: Paolo Mazza
Author-email: mazzapaolo2019@gmail.com
Requires-Python: >=3.9,<4.0
Classifier: License :: OSI Approved :: MIT License
Classifier: Programming Language :: Python :: 3
Classifier: Programming Language :: Python :: 3.9
Classifier: Programming Language :: Python :: 3.10
Classifier: Programming Language :: Python :: 3.11
Classifier: Programming Language :: Python :: 3.12
Classifier: Programming Language :: Python :: 3.13
Classifier: Programming Language :: Python :: 3.14
Requires-Dist: PyYAML (>=6.0,<7.0)
Requires-Dist: python-dotenv (>=0.21.0,<0.22.0)
Requires-Dist: requests (>=2.31.0,<3.0.0)
Project-URL: Homepage, https://github.com/ma2za/python-substack
Project-URL: Repository, https://github.com/ma2za/python-substack
